tick_delay_analysis/__init__.py
tick_delay_analysis/core.py
tick_delay_analysis/summary.py
tick_delay_analysis/scripts/run_analysis.py
tick_delay_analysis-0.1.1.dist-info/licenses/LICENSE
tick_delay_analysis-0.1.1.dist-info/METADATA
tick_delay_analysis-0.1.1.dist-info/WHEEL
tick_delay_analysis-0.1.1.dist-info/entry_points.txt
tick_delay_analysis-0.1.1.dist-info/top_level.txt
tick_delay_analysis-0.1.1.dist-info/RECORD
