Metadata-Version: 2.4
Name: tick_delay_analysis
Version: 0.1.1
Summary: A package for analyzing time delay in stock ticks
Author-email: Jingyang Peng <Eric_Peng2003@163.com>
License-Expression: MIT
Requires-Python: >=3.8
License-File: LICENSE
Requires-Dist: pandas
Requires-Dist: numpy
Requires-Dist: matplotlib
Dynamic: license-file
